{"cvePN7+ZxliUxaf95Eew7A==":"32423453452.jpg","9X5PrLrQbL5tVbjltyCC6Q==":"wizytjerzy-pawlak-2019.png","2a/fMBaiRjg4Ojoin+Jzfw==":"mbr-1920x1280.jpg","YATjVQPN9slPUePRlpmBgQ==":"plakat-2000x1993.png","AMIaIkC9KapZWclvZmMx8g==":"plakat-1-2000x1993.png","64YfwWeIxpPh8gSj871wHQ==":"plakat%202-2000x1993.png","ahIj3xmJg+Fxb1vTrxIZhA==":"plakat%203-1340x659.png","sTKFXZuFmCyTqUHMVn27Ew==":"plakat%204-1006x494.png","xvvW4UMWquqcR5zfGvbppg==":"plakat%205-263x129.png","O/rsugxgon/cLzLZtJ+RNg==":"wizyt,jerzy%20pawlak%202020-315x116.png","GlQhR081BNS5MbptSOL+bA==":"plakat%20a-1078x692.png","8mwYiR3j8oZ8jv+WXLrD0g==":"plakat%20b-748x364.png","Gq1alXTnwA07+r3/xWCGdg==":"plakat%20b-748x364.png","lomrbicOVesygBw/Ka6GIg==":"1_gda_4515187_1_-835x605.jpg","grpxFCmCWydqbtw2Hr9Tpg==":"1_gda_4515187_1_-676x490.jpg","Mxo4JqJrlQRCs9ad6VbDlw==":"400_crop_5f03428987ea4_5f00539b8f0c0-400x281.jpg","NmjbHxBzo8uBelPxqydBoA==":"400_crop_5f0342106957a_5f03419889ccc-400x281.jpg","LkrkLslWzwD7djBjRVgk6w==":"mbr-1920x1168.jpg","hFkbOArNGM/MovnPLqJcVg==":"mbr-1-1920x1280.jpg","YLzvmTpvaxtObRknUsebbQ==":"800_5f02cc68e5111-600x800.jpg","54QQRf00xIuU8JqtgMhLBA==":"800_5f02cace73bfa-436x247.jpg","aaNk9HMDELEkdGxBoCBosg==":"800_5f02cc68e5111-436x581.jpg","0wCdFf7A2S+x21nudQvz7g==":"800_5efe349458f5f-436x289.jpg","ZyswkrVAJre/JI8B/9buLQ==":"800_5f02ce9a3763f-414x630.jpg","QFZvjTNxRtpYm4H+LKA/pg==":"800_5f02cfd12686b-436x290.jpg","ksISz6Xu104906RV5WTUoA==":"800_5f02d1516dd70-436x436.jpg","pThw8z+cRxIAId6JFHLpqQ==":"800_5f0308ce6c9bc-436x270.png","SHzLEM4M9w39NAu357ihWw==":"800_5f031501d0bac-436x164.jpg","UcReXxK8x+KOI3xp5Y3jPQ==":"przechwytywanie%202-676x326.png","GTHLOChVQ9T58Ae0mj8wLg==":"przechwytywanie%202-676x326.png","63R2dmpV/lV7XQ3qa2htag==":"przechwytywanie%203-676x327.png","cPzwtcfm3qU8qu6X7I507A==":"przechwytywanie-436x228.png","ITWAMWLxGodBVHwug09qCg==":"przechwytywanie%204-436x212.png","vZIRALCPTIk1kCv4qAN4Sg==":"przechwytywanie%206-436x230.png","j4+SVyJalF1zP8kKtZOVRQ==":",,,,,,,,-436x595.png","8ANxFkanRWEL06KcfjtIJg==":"mbr-1920x823.jpg","h+ZED6Y+fURIpwYcqAHzpA==":"mbr-1920x1440.jpg","lQtOq4CYKW+iRQi7EjlCqg==":"mbr-1280x1920.jpg","8mxpnFrJLqrbEr95Nxecgg==":"mbr-1920x1271.jpg","iEDMmRIK/EiJtpuEVkkpdw==":"przechwytywanie%202-676x326.png","jvPXfzO3FX+GSVU1LbkUsA==":"1_gda_4515187_1_-676x490.jpeg","jc6d6b2zCcq7ApCwvtUnFA==":"zdjecie-676x427.jpg","sHK6GJXNTaGUlUmh4TJY5Q==":"plakat%20a-1078x692.png","OZIxuEgfiZqy6gtlJzqxTQ==":"1_gda_4515187_1_-1-676x490.jpg","ro1y79O9b+ADHZfiI6D61Q==":"400_crop_5f03428987ea4_5f00539b8f0c0-1-400x281.jpg","r6181OjuLsP0mZT2PvrERw==":"400_crop_5f0342106957a_5f03419889ccc-1-400x281.jpg","cHL/GvWNr+JbSz3zMZptYQ==":"800_5f02cace73bfa-1-436x247.jpg","rMzcp0tF2tb+hOXVjE6JIA==":",,,,,,,,-1-436x595.png","14S3DBCV/uPClqaEEP0xZA==":"800_5efe349458f5f-1-436x289.jpg","4CHuXorgCXUpbwUzhGaCjA==":"800_5f02ce9a3763f-1-414x630.jpg","GBi4pbfyBQO2aVwkt7n3mQ==":"800_5f02cfd12686b-1-436x290.jpg","r0HGbi7typaLwjcearwziw==":"800_5f02d1516dd70-1-436x436.jpg","za2aear/MjU48DXsvvQHyA==":"800_5f0308ce6c9bc-1-436x270.png","LeMCYAxxHH1d5qK8DmI61Q==":"1_gda_4515187_1_-676x574.jpg","qJgjKuBPK1AJwORnGq1Uiw==":"400_crop_5f03428987ea4_5f00539b8f0c0-453x405.jpg","dsF2OvInzEYUyfy7l76AkA==":"400_crop_5f0342106957a_5f03419889ccc-453x405.jpg","woaVyfZuCIHzumkOaSogKA==":"800_5f02cace73bfa-436x322.jpg","S4FfVmgZTUb4WdLycj7tRA==":",,,,,,,,-436x634.png","1LQmET4p7TNij/8ISNhvaw==":"800_5efe349458f5f-436x348.jpg","NUkSNuZKGyZBQZ6kGr3vYg==":"800_5f02ce9a3763f-436x716.jpg","4zDpcKL0mVUIr9FORuO5xQ==":"800_5f02cfd12686b-436x349.jpg","9wtNDHFO8eD7QncyolxhoA==":"800_5f02d1516dd70-436x515.jpg","6x+6wBWam5VjWq2WeK3wQg==":"800_5f0308ce6c9bc-436x345.png","mxUDZo79wXG96+pWXAieWQ==":"800_5f031501d0bac-436x220.jpg","RQMH3S7HmO7Qb1ITAoVqEA==":"mbr-1-1920x1271.jpg","I22zoad4HhThDYRSeJZNuA==":"mbr-1920x1278.jpg","hwe914/qTTiAkvoauj/nUw==":"mbr-1920x960.png","nNC0re9GMERdLSSQIIprQg==":"mbr-2-1920x1280.jpg","KO2udmXXHI0hR3vQI6a1aw==":"mbr-2-1920x1271.jpg","x02hq4cw4S8wPApL3tH6Iw==":"mbr-1-1920x1168.jpg","zUIV56HsSc5SgOQ2zAPDNg==":"22222-436x252.jpg","XIu4zA2pODvLIKx+qihltg==":"22222-436x283.jpg","g0O1VtyanZtTbyccwXqPGA==":"przechwytywanie-436x345.png","uNZT1TSbqcOEX3A13b3iIA==":"przechwytywanie-1-436x345.png","uK/cHTZCYekAlgQfWZn46w==":"przechwytywanie-2-436x345.png","v2dG+DenYeAryXR1/yOrbA==":"mbr-2-1920x1168.jpg"}